LICENSE
MANIFEST.in
README.md
setup.cfg
setup.py
test-travis.sh
test.sh
mininero_ph4.egg-info/PKG-INFO
mininero_ph4.egg-info/SOURCES.txt
mininero_ph4.egg-info/dependency_links.txt
mininero_ph4.egg-info/requires.txt
mininero_ph4.egg-info/top_level.txt
mnero/ASNL.py
mnero/Keccak.py
mnero/MLSAG2.py
mnero/PaperWallet.py
mnero/RingCT2.py
mnero/__init__.py
mnero/ed25519.py
mnero/ed25519_2.py
mnero/ed25519ietf.py
mnero/keccak2.py
mnero/mininero.py
mnero/mnemonic.py
mnero/docs/LICENSE
mnero_test/__init__.py
mnero_test/test_basic.py