Metadata-Version: 1.1
Name: mininero-ph4
Version: 0.0.1
Summary: Mininero Ph4 port
Home-page: https://github.com/ph4r05/mininero-ph4
Author: Dusan Klinec
Author-email: dusan.klinec@gmail.com
License: MIT
Platform: UNKNOWN
Classifier: Development Status :: 3 - Alpha
Classifier: Intended Audience :: Developers
Classifier: Programming Language :: Python
Classifier: Programming Language :: Python :: 3.5
Classifier: Programming Language :: Python :: 3.6
Classifier: Topic :: Security
